smartg/Voigt_gpu.py
smartg/__init__.py
smartg/albedo.py
smartg/atmosphere.py
smartg/auxdata.py
smartg/bandset.py
smartg/cli.py
smartg/config.py
smartg/conftest.py
smartg/diffgeom.py
smartg/geometry.py
smartg/histories.py
smartg/iprt.py
smartg/kdis.py
smartg/lib3D.py
smartg/libATM3D.py
smartg/reptran.py
smartg/rrs.py
smartg/shape.py
smartg/smartg.py
smartg/transform.py
smartg/visualizegeo.py
smartg/vrs.py
smartg/water.py
smartg/notebooks/demo_notebook.ipynb
smartg/notebooks/demo_notebook_objects.ipynb
smartg/src/communs.h
smartg/src/device.cu
smartg/src/device.h
smartg/src/geometry.h
smartg/src/helper_math.h
smartg/src/kernel2.cu
smartg/src/kernel2.h
smartg/src/math_constants.h
smartg/src/shapes.h
smartg/src/transform.h
smartg/src/incRNGs/Random123/MicroURNG.hpp
smartg/src/incRNGs/Random123/ReinterpretCtr.hpp
smartg/src/incRNGs/Random123/aes.h
smartg/src/incRNGs/Random123/array.h
smartg/src/incRNGs/Random123/ars.h
smartg/src/incRNGs/Random123/gsl_microrng.h
smartg/src/incRNGs/Random123/philox.h
smartg/src/incRNGs/Random123/threefry.h
smartg/src/incRNGs/Random123/conventional/Engine.hpp
smartg/src/incRNGs/Random123/conventional/gsl_cbrng.h
smartg/src/incRNGs/Random123/features/clangfeatures.h
smartg/src/incRNGs/Random123/features/compilerfeatures.h
smartg/src/incRNGs/Random123/features/gccfeatures.h
smartg/src/incRNGs/Random123/features/iccfeatures.h
smartg/src/incRNGs/Random123/features/msvcfeatures.h
smartg/src/incRNGs/Random123/features/nvccfeatures.h
smartg/src/incRNGs/Random123/features/open64features.h
smartg/src/incRNGs/Random123/features/openclfeatures.h
smartg/src/incRNGs/Random123/features/pgccfeatures.h
smartg/src/incRNGs/Random123/features/sse.h
smartg/src/incRNGs/Random123/features/sunprofeatures.h
smartg/src/incRNGs/Random123/features/xlcfeatures.h
smartg/tests/__init__.py
smartg/tests/test_OPAC.py
smartg/tests/test_cuda.py
smartg/tests/test_notebook.py
smartg/tests/test_profile.py
smartg/tests/test_quick_iprt_phaseA.py
smartg/tests/test_smartg.py
smartg-1.1.0.dist-info/licenses/LICENSE.TXT
smartg-1.1.0.dist-info/licenses/LICENSE_RNG.TXT
smartg-1.1.0.dist-info/METADATA
smartg-1.1.0.dist-info/WHEEL
smartg-1.1.0.dist-info/top_level.txt
smartg-1.1.0.dist-info/RECORD
