Metadata-Version: 2.4
Name: smartg
Version: 1.1.0
Summary: SMART-G (Speed-up Monte Carlo Advanced Radiative Transfer Code using GPU) is a radiative transfer code using a Monte-Carlo technique to simulate the propagation of the polarized light in the atmosphere and/or ocean, and using GPU acceleration.
Author-email: Mustapha Moulana <mm@hygeos.com>, Didier Ramon <dr@hygeos.com>, François Steinmetz <fs@hygeos.com>, Dominique Jolivet <dj@hygeos.com>, Mathieu Compiègne <mc@hygeos.com>
Project-URL: Source, https://github.com/hygeos/smartg
Classifier: Development Status :: 5 - Production/Stable
Classifier: License :: Free for non-commercial use
Classifier: License :: Other/Proprietary License
Classifier: Intended Audience :: Science/Research
Classifier: Intended Audience :: Developers
Classifier: Programming Language :: Python
Classifier: Programming Language :: Python :: 3.10
Classifier: Programming Language :: Python :: 3.11
Classifier: Programming Language :: Python :: 3.12
Classifier: Programming Language :: Python :: 3.13
Classifier: Topic :: Scientific/Engineering
Requires-Python: <3.14,>=3.10
License-File: LICENSE.TXT
License-File: LICENSE_RNG.TXT
Requires-Dist: numpy
Requires-Dist: pandas
Requires-Dist: scipy
Requires-Dist: h5py
Requires-Dist: pyarrow
Requires-Dist: openpyxl
Requires-Dist: progressbar2
Requires-Dist: matplotlib
Requires-Dist: python-dotenv
Requires-Dist: notebook
Requires-Dist: ipywidgets
Requires-Dist: ipympl
Requires-Dist: pyhdf
Requires-Dist: pycuda
Requires-Dist: geoclide
Requires-Dist: luts
Requires-Dist: hitran-api
Provides-Extra: test
Requires-Dist: pytest; extra == "test"
Requires-Dist: pytest-xdist; extra == "test"
Requires-Dist: pytest-html; extra == "test"
Requires-Dist: papermill; extra == "test"
Provides-Extra: extra
Requires-Dist: gatiab; extra == "extra"
Requires-Dist: statsmodels; extra == "extra"
Requires-Dist: jax[cuda12]; extra == "extra"
Dynamic: license-file
